zypper_changelog_lib/__init__.py
zypper_changelog_lib/__main__.py
zypper_changelog_lib/zyppchangelog.py
zypper_changelog_lib-0.7.9.dist-info/LICENSES/CC-BY-SA-4.0.txt
zypper_changelog_lib-0.7.9.dist-info/LICENSES/CC0-1.0.txt
zypper_changelog_lib-0.7.9.dist-info/LICENSES/GPL-3.0-or-later.txt
zypper_changelog_lib-0.7.9.dist-info/LICENSES/LGPL-2.1-only.txt
zypper_changelog_lib-0.7.9.dist-info/METADATA
zypper_changelog_lib-0.7.9.dist-info/WHEEL
zypper_changelog_lib-0.7.9.dist-info/entry_points.txt
zypper_changelog_lib-0.7.9.dist-info/RECORD
