Metadata-Version: 2.1
Name: zypper-changelog-lib
Version: 0.7.9
Summary: Changelogs for installable pending updates, or available/uninstalled packages
Home-page: https://codeberg.org/Rockstor/zypper-changelog-lib
License: LGPL-2.1-only AND GPL-3.0-or-later
Keywords: linux,zypper,changelog,openSUSE
Author: The Rockstor Project
Author-email: support@rockstor.com
Maintainer: Philip Paul Guyton
Maintainer-email: support@rockstor.com
Requires-Python: >=3.11,<4.0
Classifier: Development Status :: 4 - Beta
Classifier: Intended Audience :: Developers
Classifier: License :: CC0 1.0 Universal (CC0 1.0) Public Domain Dedication
Classifier: License :: OSI Approved :: GNU General Public License v3 or later (GPLv3+)
Classifier: License :: OSI Approved :: GNU Lesser General Public License v2 (LGPLv2)
Classifier: License :: Other/Proprietary License
Classifier: Natural Language :: English
Classifier: Operating System :: POSIX :: Linux
Classifier: Programming Language :: Python :: 3
Classifier: Programming Language :: Python :: 3.11
Classifier: Programming Language :: Python :: 3.12
Classifier: Topic :: Software Development :: Libraries :: Python Modules
Requires-Dist: keyring-pass
Requires-Dist: requests
Requires-Dist: rpm
Project-URL: Repository, https://codeberg.org/Rockstor/zypper-changelog-lib
